urlgraph/__init__.py
urlgraph/__main__.py
urlgraph-0.1.1.dist-info/METADATA
urlgraph-0.1.1.dist-info/WHEEL
urlgraph-0.1.1.dist-info/RECORD
