Metadata-Version: 2.1
Name: urlgraph
Version: 0.1.1
Summary: 
Author: Piotr Żarczyński
Author-email: piotr.zarczynski.06@gmail.com
Requires-Python: >=3.11,<4.0
Classifier: Programming Language :: Python :: 3
Classifier: Programming Language :: Python :: 3.11
Classifier: Programming Language :: Python :: 3.12
Requires-Dist: aiodns (>=3.1.1,<4.0.0)
Requires-Dist: aiohttp (>=3.9.3,<4.0.0)
Requires-Dist: alive-progress (>=3.1.5,<4.0.0)
Requires-Dist: beautifulsoup4 (>=4.12.3,<5.0.0)
Requires-Dist: black (>=24.1.1,<25.0.0)
Requires-Dist: fire (>=0.5.0,<0.6.0)
Requires-Dist: isort (>=5.13.2,<6.0.0)
Requires-Dist: pyvis (>=0.3.2,<0.4.0)
